pyrepetier/__init__.py
pyrepetier/clsprinter.py
pyrepetier/clsserver.py
pyrepetier-3.0.5.dist-info/METADATA
pyrepetier-3.0.5.dist-info/WHEEL
pyrepetier-3.0.5.dist-info/top_level.txt
pyrepetier-3.0.5.dist-info/RECORD
