Metadata-Version: 2.1
Name: pyrepetier
Version: 3.0.5
Summary: Repetier Server API library
Home-page: https://github.com/mtrab/pyrepetier
Author: Morten Trab
Author-email: morten@trab.dk
License: MIT
Platform: UNKNOWN
